{
  "inputDatasetSmartName": "train",
  "script": {
    "steps": [],
    "maxProcessedMemTableBytes": -1,
    "columnsSelection": {
      "mode": "ALL"
    },
    "columnWidthsByName": {},
    "columnUseScientificNotationByName": {},
    "coloring": {
      "scheme": "MEANING_AND_STATUS",
      "individualColumns": [],
      "valueColoringMode": "HASH"
    },
    "sorting": [],
    "analysisColumnData": {
      "fraudulent": {
        "comment": "0 - real; 1 - fake job"
      }
    },
    "explorationSampling": {
      "selection": {
        "maxRecordsForDisplay": -1,
        "maxStoredBytes": 104857600,
        "timeout": -1,
        "filter": {
          "distinct": false,
          "enabled": false
        },
        "partitionSelectionMethod": "ALL",
        "latestPartitionsN": 1,
        "ordering": {
          "enabled": false,
          "rules": []
        },
        "samplingMethod": "HEAD_SEQUENTIAL",
        "maxRecords": 10000,
        "targetRatio": 0.02,
        "withinFirstN": -1,
        "maxReadUncompressedBytes": -1
      },
      "autoRefreshSample": false,
      "_refreshTrigger": 0
    },
    "vizSampling": {
      "selection": {
        "useMemTable": false,
        "filter": {
          "distinct": false,
          "enabled": false
        },
        "partitionSelectionMethod": "ALL",
        "latestPartitionsN": 1,
        "ordering": {
          "enabled": false,
          "rules": []
        },
        "samplingMethod": "FULL",
        "maxRecords": -1,
        "targetRatio": 0.02,
        "withinFirstN": -1,
        "maxReadUncompressedBytes": -1
      },
      "autoRefreshSample": false,
      "_refreshTrigger": 0
    },
    "exploreUIParams": {},
    "globalSearchQuery": "",
    "explorationFilters": [],
    "previewMode": "ALL_ROWS"
  },
  "charts": [],
  "name": "Quick modeling of fraudulent on train",
  "versionTag": {
    "versionNumber": 0,
    "lastModifiedBy": {
      "login": "sean"
    },
    "lastModifiedOn": 1688407821070,
    "extendedProperties": {}
  },
  "creationTag": {
    "versionNumber": 0,
    "lastModifiedBy": {
      "login": "sean"
    },
    "lastModifiedOn": 1688407821070,
    "extendedProperties": {}
  },
  "tags": [],
  "customFields": {},
  "checklists": {
    "checklists": []
  }
}